{"variants":[{"traits":[{"interfaceLanguage":"swift"}],"paths":["\/documentation\/soulvercore\/dateparsing"]}],"hierarchy":{"paths":[["doc:\/\/app.soulver.core\/documentation\/SoulverCore"]]},"abstract":[{"type":"text","text":"Add a natural language date scheduling feature to your Mac or iOS calendar or reminders app"}],"identifier":{"url":"doc:\/\/app.soulver.core\/documentation\/SoulverCore\/DateParsing","interfaceLanguage":"swift"},"primaryContentSections":[{"content":[{"level":2,"type":"heading","text":"Motivation","anchor":"Motivation"},{"inlineContent":[{"type":"text","text":"Natural language date input features can be found in apps like "},{"isActive":true,"identifier":"https:\/\/culturedcode.com\/things\/support\/articles\/9780167\/","type":"reference"},{"type":"text","text":", "},{"type":"reference","identifier":"https:\/\/flexibits.com\/fantastical-ios\/help\/adding","isActive":true},{"type":"text","text":" and "},{"type":"reference","identifier":"https:\/\/www.raycast.com\/extensions\/reminders","isActive":true},{"text":" and make the user experience better.","type":"text"}],"type":"paragraph"},{"text":"Usage","anchor":"Usage","type":"heading","level":2},{"type":"paragraph","inlineContent":[{"type":"codeVoice","code":"SoulverCore"},{"type":"text","text":" adds a single property "},{"code":"dateValue","type":"codeVoice"},{"type":"text","text":" to "},{"type":"codeVoice","code":"String"},{"text":":","type":"text"}]},{"code":["public extension String {","   var dateValue: Date?","}"],"type":"codeListing","syntax":"swift"},{"type":"paragraph","inlineContent":[{"type":"text","text":"Use this property to extract the last natural language date found in the string. The "},{"code":"dateValue","type":"codeVoice"},{"text":" will be ","type":"text"},{"type":"codeVoice","code":"nil"},{"type":"text","text":" if there are no dates in the string."}]},{"anchor":"SoulverCore-vs-Foundations-DataDetector","text":"SoulverCore vs Foundation’s DataDetector","level":2,"type":"heading"},{"type":"paragraph","inlineContent":[{"type":"text","text":"Apple’s Foundation framework includes NSDataDetector for detecting dates in strings."}]},{"type":"paragraph","inlineContent":[{"type":"text","text":"Here is an example:"}]},{"type":"codeListing","code":["let expression = \"March 5th, 2023\"","let types: NSTextCheckingResult.CheckingType = [.date ]","let detector = try! NSDataDetector(types: types.rawValue)","let match = detector.matches(in: expression, options: .init(rawValue: 0), range: NSRange(location: 0, length: expression.count)).first","let date = match?.date"],"syntax":"swift"},{"type":"paragraph","inlineContent":[{"type":"text","text":"Compare this to SoulverCore:"}]},{"type":"codeListing","syntax":"swift","code":["let date = \"March 5th, 2023\".dateValue"]},{"type":"paragraph","inlineContent":[{"type":"text","text":"In addition to a much nicer API, SoulverCore also adds a number of additional features not supported by NSDataDetector."}]},{"text":"Supported Features","type":"heading","level":2,"anchor":"Supported-Features"},{"type":"heading","anchor":"Natural-language-calendar-math","text":"Natural language calendar math","level":4},{"type":"paragraph","inlineContent":[{"text":"Use natural language phrases like “3 weeks from tomorrow” and “march 12 + 4 weeks 3 days”.","type":"text"}]},{"inlineContent":[{"text":"SoulverCore supports a large range of different natural language date syntaxes. See the ","type":"text"},{"isActive":true,"identifier":"https:\/\/documentation.soulver.app\/syntax-reference\/dates-and-times","type":"reference"},{"text":" for more examples.","type":"text"}],"type":"paragraph"},{"anchor":"Units--unit-shorthands","text":"Units & unit shorthands","level":4,"type":"heading"},{"type":"paragraph","inlineContent":[{"text":"SoulverCore interprets units of time as referring to a future date after the specified amount of time has passed.","type":"text"}]},{"type":"paragraph","inlineContent":[{"type":"text","text":"For example "},{"type":"codeVoice","code":"2 weeks 2 days"},{"type":"text","text":" will be interpreted as "},{"code":"2 weeks and 2 days","type":"codeVoice"},{"type":"text","text":" "},{"type":"strong","inlineContent":[{"text":"from now","type":"text"}]},{"type":"text","text":"."}]},{"type":"paragraph","inlineContent":[{"type":"text","text":"The following time unit shorthands are also supported:"}]},{"items":[{"content":[{"inlineContent":[{"text":"“1y” (1 year)","type":"text"}],"type":"paragraph"}]},{"content":[{"inlineContent":[{"type":"text","text":"“5mo” (5 months)"}],"type":"paragraph"}]},{"content":[{"type":"paragraph","inlineContent":[{"type":"text","text":"“3w” (3 weeks)"}]}]},{"content":[{"type":"paragraph","inlineContent":[{"text":"“2d” (2 days)","type":"text"}]}]}],"type":"unorderedList"},{"type":"paragraph","inlineContent":[{"type":"text","text":"Shorthands can be combined together:"}]},{"type":"unorderedList","items":[{"content":[{"type":"paragraph","inlineContent":[{"type":"text","text":"“12-9 9p” means the “12th of September at 9pm” (in a non-US locale)"}]}]}]},{"text":"Half-formed dates","level":4,"type":"heading","anchor":"Half-formed-dates"},{"type":"paragraph","inlineContent":[{"text":"Examples:","type":"text"}]},{"items":[{"content":[{"inlineContent":[{"type":"text","text":"“3\/12” (Dec 3, or March 12 in the US)"}],"type":"paragraph"}]},{"content":[{"inlineContent":[{"type":"text","text":"“12.2” (Feb 12 or Dec 2 in the US)"}],"type":"paragraph"}]},{"content":[{"type":"paragraph","inlineContent":[{"text":"“9-5” (May 9 or Sep 5 in the US)","type":"text"}]}]}],"type":"unorderedList"},{"type":"heading","text":"Day & month shorthands","level":4,"anchor":"Day--month-shorthands"},{"type":"paragraph","inlineContent":[{"text":"Examples:","type":"text"}]},{"type":"unorderedList","items":[{"content":[{"inlineContent":[{"text":"“Next mon” (next monday)","type":"text"}],"type":"paragraph"}]},{"content":[{"type":"paragraph","inlineContent":[{"text":"“tod” (today)","type":"text"}]}]},{"content":[{"type":"paragraph","inlineContent":[{"text":"“apr3” (April 3)","type":"text"}]}]},{"content":[{"inlineContent":[{"type":"text","text":"“yes” (yesterday)"}],"type":"paragraph"}]},{"content":[{"type":"paragraph","inlineContent":[{"type":"text","text":"“tom” (tomorrow)"}]}]}]},{"text":"AM\/PM shorthands","type":"heading","anchor":"AMPM-shorthands","level":4},{"inlineContent":[{"text":"Examples:","type":"text"}],"type":"paragraph"},{"type":"unorderedList","items":[{"content":[{"inlineContent":[{"type":"text","text":"“3p” (3pm)"}],"type":"paragraph"}]},{"content":[{"inlineContent":[{"type":"text","text":"“5a” (5am)"}],"type":"paragraph"}]}]},{"text":"Random words ignored","level":4,"anchor":"Random-words-ignored","type":"heading"},{"type":"paragraph","inlineContent":[{"text":"SoulverCore extracts the last date present in the given string, and ignores random words before and after it.","type":"text"}]},{"type":"paragraph","inlineContent":[{"text":"For example, the following are valid inputs:","type":"text"}]},{"items":[{"content":[{"type":"paragraph","inlineContent":[{"type":"text","text":"“Tom’s birthday party "},{"type":"strong","inlineContent":[{"type":"text","text":"this sunday"}]},{"text":"”","type":"text"}]}]},{"content":[{"inlineContent":[{"type":"text","text":"“Schedule the meeting for "},{"type":"strong","inlineContent":[{"type":"text","text":"April 21st next year"}]},{"text":"”","type":"text"}],"type":"paragraph"}]},{"content":[{"inlineContent":[{"type":"text","text":"“"},{"type":"strong","inlineContent":[{"type":"text","text":"June 5"}]},{"text":" the kids get off school”","type":"text"}],"type":"paragraph"}]}],"type":"unorderedList"},{"type":"heading","level":2,"anchor":"Detailed-information-about-the-parsed-date","text":"Detailed information about the parsed date"},{"type":"paragraph","inlineContent":[{"type":"text","text":"The "},{"identifier":"doc:\/\/app.soulver.core\/documentation\/SoulverCore\/Datestamp\/DatestampType","isActive":true,"type":"reference"},{"type":"text","text":" enum contains detailed information about the kind of date detected and what date components were explicitly specified."}]},{"type":"paragraph","inlineContent":[{"type":"text","text":"Here is how an example of how to get the formatting and components of the detected date:"}]},{"type":"codeListing","syntax":"swift","code":["var engineCustomization = EngineCustomization.standard","engineCustomization.featureFlags.seeksFutureDate = true","let calculator = Calculator(customization: engineCustomization)","","if let datestampType = calculator.dateFor(inputDateText)?.result.evaluationResult.datestampValue?.type {","    print(\"Date of type \\(datestampType)\")","}"]},{"anchor":"Performance","text":"Performance","level":2,"type":"heading"},{"type":"paragraph","inlineContent":[{"type":"text","text":"SoulverCore is very efficient and can perform thousands of date-from-string extractions every second."}]},{"level":2,"text":"Localizations","type":"heading","anchor":"Localizations"},{"inlineContent":[{"text":"In addition to English, SoulverCore is localized into German, French, Spanish, Russian & Simplified Chinese.","type":"text"}],"type":"paragraph"},{"type":"paragraph","inlineContent":[{"text":"The user’s system locale will be used for date parsing, and date & time formats specific the particular region are taken into account.","type":"text"}]}],"kind":"content"}],"kind":"article","sections":[],"metadata":{"modules":[{"name":"SoulverCore"}],"title":"Natural language date parsing","role":"article","roleHeading":"Article"},"schemaVersion":{"major":0,"patch":0,"minor":3},"seeAlsoSections":[{"generated":true,"title":"String extensions for quick data parsing","identifiers":["doc:\/\/app.soulver.core\/documentation\/SoulverCore\/DataParsing"]}],"references":{"doc://app.soulver.core/documentation/SoulverCore":{"type":"topic","title":"SoulverCore","identifier":"doc:\/\/app.soulver.core\/documentation\/SoulverCore","url":"\/documentation\/soulvercore","kind":"symbol","abstract":[{"text":"A powerful natural language calculation engine","type":"text"}],"role":"collection"},"https://flexibits.com/fantastical-ios/help/adding":{"title":"Fantastical","identifier":"https:\/\/flexibits.com\/fantastical-ios\/help\/adding","url":"https:\/\/flexibits.com\/fantastical-ios\/help\/adding","titleInlineContent":[{"type":"text","text":"Fantastical"}],"type":"link"},"doc://app.soulver.core/documentation/SoulverCore/DataParsing":{"role":"article","url":"\/documentation\/soulvercore\/dataparsing","abstract":[{"type":"text","text":"A declarative & type-safe approach to extracting various data types out of strings"}],"identifier":"doc:\/\/app.soulver.core\/documentation\/SoulverCore\/DataParsing","kind":"article","title":"Data from string parsing","type":"topic"},"https://documentation.soulver.app/syntax-reference/dates-and-times":{"title":"Soulver Documentation","identifier":"https:\/\/documentation.soulver.app\/syntax-reference\/dates-and-times","url":"https:\/\/documentation.soulver.app\/syntax-reference\/dates-and-times","titleInlineContent":[{"type":"text","text":"Soulver Documentation"}],"type":"link"},"https://culturedcode.com/things/support/articles/9780167/":{"titleInlineContent":[{"type":"text","text":"Things"}],"identifier":"https:\/\/culturedcode.com\/things\/support\/articles\/9780167\/","type":"link","url":"https:\/\/culturedcode.com\/things\/support\/articles\/9780167\/","title":"Things"},"doc://app.soulver.core/documentation/SoulverCore/Datestamp/DatestampType":{"url":"\/documentation\/soulvercore\/datestamp\/datestamptype","fragments":[{"text":"enum","kind":"keyword"},{"kind":"text","text":" "},{"kind":"identifier","text":"DatestampType"}],"navigatorTitle":[{"text":"DatestampType","kind":"identifier"}],"title":"Datestamp.DatestampType","role":"symbol","abstract":[{"type":"text","text":"The types of datestamps supported by SoulverCore"}],"kind":"symbol","identifier":"doc:\/\/app.soulver.core\/documentation\/SoulverCore\/Datestamp\/DatestampType","type":"topic"},"https://www.raycast.com/extensions/reminders":{"title":"Raycast","identifier":"https:\/\/www.raycast.com\/extensions\/reminders","url":"https:\/\/www.raycast.com\/extensions\/reminders","titleInlineContent":[{"type":"text","text":"Raycast"}],"type":"link"}}}